pydiff_planetarium_assignment/__init__.py
pydiff_planetarium_assignment/diff.py
pydiff_planetarium_assignment/print.py
pydiff_planetarium_assignment/pydiff.py
pydiff_planetarium_assignment-0.0.8.dist-info/METADATA
pydiff_planetarium_assignment-0.0.8.dist-info/WHEEL
pydiff_planetarium_assignment-0.0.8.dist-info/top_level.txt
pydiff_planetarium_assignment-0.0.8.dist-info/RECORD
