Metadata-Version: 2.1
Name: pydiff-planetarium-assignment
Version: 0.0.8
Summary: Simple implementation of unix diff
Home-page: https://github.com/planetarium/take-home-2023-channprj
Author: channprj
Author-email: chann@chann.dev
Project-URL: Bug Tracker, https://github.com/planetarium/take-home-2023-channprj/issues
Classifier: Programming Language :: Python :: 3 :: Only
Requires-Python: >=3.8
